logpy.py
setup.py
LogPy.egg-info/PKG-INFO
LogPy.egg-info/SOURCES.txt
LogPy.egg-info/dependency_links.txt
LogPy.egg-info/top_level.txt