Metadata-Version: 1.0
Name: LogPy
Version: 1.0
Summary: Unorthodox logging for python
Home-page: http://github.com/MHordecki/LogPy
Author: Michal Hordecki
Author-email: mhordecki@gmail.com
License: UNKNOWN
Platform: UNKNOWN
Classifier: Programming Language :: Python :: 3
Classifier: Topic :: Software Development :: Libraries
Classifier: License :: OSI Approved :: BSD License
Classifier: Programming Language :: Python :: 2.6
Classifier: Programming Language :: Python :: 2.7
